googlesheets2csv/__init__.py
googlesheets2csv/download.py
googlesheets2csv/scripts/__init__.py
googlesheets2csv/scripts/cli.py
googlesheets2csv-0.1.0.dist-info/METADATA
googlesheets2csv-0.1.0.dist-info/WHEEL
googlesheets2csv-0.1.0.dist-info/entry_points.txt
googlesheets2csv-0.1.0.dist-info/licenses/LICENSE
googlesheets2csv-0.1.0.dist-info/RECORD
