Metadata-Version: 2.1
Name: googlesheets2csv
Version: 0.1.0
Summary: Export google spreadsheet to csv, you can filter data with SQL statement.
Project-URL: Homepage, https://github.com/YuChunTsao/googlesheets2csv
Author-email: YuChunTsao <tsao84672776@gmail.com>
License: MIT License
License-File: LICENSE
Classifier: License :: OSI Approved :: MIT License
Classifier: Operating System :: OS Independent
Classifier: Programming Language :: Python :: 3
Requires-Python: >=3.7
Requires-Dist: duckdb
Requires-Dist: gspread
Requires-Dist: pandas
